linodecli/__init__.py
linodecli/__main__.py
linodecli/api_request.py
linodecli/arg_helpers.py
linodecli/cli.py
linodecli/completion.py
linodecli/data-3
linodecli/exit_codes.py
linodecli/help_pages.py
linodecli/helpers.py
linodecli/oauth-landing-page.html
linodecli/overrides.py
linodecli/version.py
linodecli/baked/__init__.py
linodecli/baked/operation.py
linodecli/baked/parsing.py
linodecli/baked/request.py
linodecli/baked/response.py
linodecli/baked/util.py
linodecli/configuration/__init__.py
linodecli/configuration/auth.py
linodecli/configuration/config.py
linodecli/configuration/helpers.py
linodecli/output/__init__.py
linodecli/output/helpers.py
linodecli/output/output_handler.py
linodecli/plugins/__init__.py
linodecli/plugins/firewall-editor.py
linodecli/plugins/get-kubeconfig.py
linodecli/plugins/image-upload.py
linodecli/plugins/metadata.py
linodecli/plugins/plugins.py
linodecli/plugins/region-table.py
linodecli/plugins/ssh.py
linodecli/plugins/obj/__init__.py
linodecli/plugins/obj/buckets.py
linodecli/plugins/obj/config.py
linodecli/plugins/obj/helpers.py
linodecli/plugins/obj/list.py
linodecli/plugins/obj/objects.py
linodecli/plugins/obj/website.py
zliang_linode_cli_test_publishing-0.0.1.dist-info/licenses/LICENSE
zliang_linode_cli_test_publishing-0.0.1.dist-info/METADATA
zliang_linode_cli_test_publishing-0.0.1.dist-info/WHEEL
zliang_linode_cli_test_publishing-0.0.1.dist-info/entry_points.txt
zliang_linode_cli_test_publishing-0.0.1.dist-info/top_level.txt
zliang_linode_cli_test_publishing-0.0.1.dist-info/RECORD
